overboard_logger/__init__.py
overboard_logger/logger.py
overboard_logger-0.7.1.dist-info/METADATA
overboard_logger-0.7.1.dist-info/WHEEL
overboard_logger-0.7.1.dist-info/top_level.txt
overboard_logger-0.7.1.dist-info/RECORD
