Metadata-Version: 2.1
Name: overboard-logger
Version: 0.7.1
Summary: Stand-alone logger class for OverBoard -- Pure Python dashboard for monitoring deep learning experiments
Home-page: https://github.com/jotaf98/overboard
Author: Joao Henriques
License: UNKNOWN
Platform: UNKNOWN
Classifier: Programming Language :: Python :: 3
Classifier: License :: OSI Approved :: GNU General Public License v3 (GPLv3)
Classifier: Operating System :: OS Independent
